geochunk/__init__.py
geochunk-0.0.1.dist-info/METADATA
geochunk-0.0.1.dist-info/WHEEL
geochunk-0.0.1.dist-info/top_level.txt
geochunk-0.0.1.dist-info/RECORD
