Metadata-Version: 2.4
Name: geochunk
Version: 0.0.1
Summary: Unified access protocol for geospatiotemporal data sources
Author-email: paul <paul@socialtechnologylab.com>
License: MIT
Project-URL: Homepage, https://github.com/socialtechnologylab/geochunk
Project-URL: Repository, https://github.com/socialtechnologylab/geochunk
Classifier: Development Status :: 2 - Pre-Alpha
Classifier: Intended Audience :: Developers
Classifier: License :: OSI Approved :: MIT License
Classifier: Programming Language :: Python :: 3
Classifier: Topic :: Scientific/Engineering :: GIS
Requires-Python: >=3.8
